CHANGELOG.rst
COPYING
COPYING.LESSER
INSTALL.rst
MANIFEST.in
README.rst
cgmp.pxd
cmpfr.pxd
mpfr.c
mpfr.pyx
setup.py
bigfloat/__init__.py
bigfloat/context.py
bigfloat/core.py
bigfloat/formatting.py
bigfloat/ieee.py
bigfloat/mpfr_supplemental.py
bigfloat/rounding_mode.py
bigfloat/version.py
bigfloat.egg-info/PKG-INFO
bigfloat.egg-info/SOURCES.txt
bigfloat.egg-info/dependency_links.txt
bigfloat.egg-info/requires.txt
bigfloat.egg-info/top_level.txt
bigfloat/test/__init__.py
bigfloat/test/test___all__.py
bigfloat/test/test_bigfloat.py
bigfloat/test/test_context.py
bigfloat/test/test_formatting.py
bigfloat/test/test_mpfr.py
bigfloat/test/test_rounding_mode.py
docs/Makefile
docs/source/conf.py
docs/source/index.rst
docs/source/reference/index.rst
docs/source/tutorial/index.rst
examples/contfrac.py
examples/lanczos_coeffs.py