Metadata-Version: 2.1
Name: bigfloat
Version: 0.4.0
Summary: Arbitrary-precision correctly-rounded floating-point arithmetic, via MPFR.
Home-page: http://github.com/mdickinson/bigfloat
Author: Mark Dickinson
Author-email: dickinsm@gmail.com
License: GNU Library or Lesser General Public License (LGPL)
Platform: Linux
Platform: OS X
Classifier: Development Status :: 4 - Beta
Classifier: Intended Audience :: Developers
Classifier: Intended Audience :: Education
Classifier: Intended Audience :: Science/Research
Classifier: License :: OSI Approved :: GNU Lesser General Public License v3 (LGPLv3)
Classifier: Operating System :: OS Independent
Classifier: Programming Language :: Python :: 2
Classifier: Programming Language :: Python :: 2.7
Classifier: Programming Language :: Python :: 3
Classifier: Programming Language :: Python :: 3.5
Classifier: Programming Language :: Python :: 3.6
Classifier: Programming Language :: Python :: 3.7
Classifier: Programming Language :: Python :: 3.8
Classifier: Programming Language :: Python :: Implementation :: CPython
Classifier: Topic :: Scientific/Engineering :: Mathematics
